azureml/__init__.py
azureml/contrib/__init__.py
azureml/contrib/_rlservice/__init__.py
azureml/contrib/_rlservice/_commands.py
azureml/contrib/compute/__init__.py
azureml/contrib/compute/_amlWindowsCompute.py
azureml/contrib/compute/amlwindowscompute_cluster_template.json
azureml/contrib/train/__init__.py
azureml/contrib/train/rl/__init__.py
azureml/contrib/train/rl/_rl_base_estimator.py
azureml/contrib/train/rl/_rl_environment_helper.py
azureml/contrib/train/rl/_rl_estimator.py
azureml/contrib/train/rl/_rl_framework.py
azureml/contrib/train/rl/_rl_run.py
azureml/contrib/train/rl/_rl_runconfig.py
azureml/contrib/train/rl/_cli/__init__.py
azureml/contrib/train/rl/_cli/_rl_run_submit.py
azureml/contrib/train/rl/_client/__init__.py
azureml/contrib/train/rl/_client/swagger/__init__.py
azureml/contrib/train/rl/_client/swagger/reinforcement_learning_service_api.py
azureml/contrib/train/rl/_client/swagger/version.py
azureml/contrib/train/rl/_client/swagger/models/__init__.py
azureml/contrib/train/rl/_client/swagger/models/error_response.py
azureml/contrib/train/rl/_client/swagger/models/error_response_py3.py
azureml/contrib/train/rl/_client/swagger/models/inner_error_response.py
azureml/contrib/train/rl/_client/swagger/models/inner_error_response_py3.py
azureml/contrib/train/rl/_client/swagger/models/root_error.py
azureml/contrib/train/rl/_client/swagger/models/root_error_py3.py
azureml/contrib/train/rl/_client/swagger/models/run_details.py
azureml/contrib/train/rl/_client/swagger/models/run_details_py3.py
azureml/contrib/train/rl/_client/swagger/operations/__init__.py
azureml/contrib/train/rl/_client/swagger/operations/reinforcement_learning_operations.py
azureml/contrib/train/rl/scenarios/ray-0.8.0-cpu.yml
azureml/contrib/train/rl/scenarios/ray-0.8.0-gpu.yml
azureml/contrib/train/rl/scenarios/ray-0.8.3-cpu.yml
azureml/contrib/train/rl/scenarios/ray-0.8.3-gpu.yml
azureml/contrib/train/rl/utils/__init__.py
azureml/contrib/train/rl/utils/rl_deprecation.py
azureml_contrib_reinforcementlearning-1.60.0.dist-info/licenses/LICENSE.txt
tests/__init__.py
azureml_contrib_reinforcementlearning-1.60.0.dist-info/METADATA
azureml_contrib_reinforcementlearning-1.60.0.dist-info/WHEEL
azureml_contrib_reinforcementlearning-1.60.0.dist-info/top_level.txt
azureml_contrib_reinforcementlearning-1.60.0.dist-info/RECORD
