Metadata-Version: 2.4
Name: azureml-contrib-reinforcementlearning
Version: 1.60.0
Summary: Provides preview feature for AzureML Python SDK that allows     to submit Reinforcement Learning runs. NOTE: Service is being deprecated.     See https://aka.ms/rldeprecation for more information and timelines.
Home-page: https://docs.microsoft.com/python/api/overview/azure/ml/?view=azure-ml-py
Author: Microsoft Corp
License: Proprietary https://aka.ms/azureml-preview-sdk-license 
Keywords: Reinforcement Learning,RL
Requires-Python: >=3.7,<4.0
License-File: LICENSE.txt
Requires-Dist: requests>=2.19.1
Requires-Dist: msrest>=0.5.1
Requires-Dist: msrestazure>=0.4.33
Requires-Dist: azureml-core~=1.60.0
Requires-Dist: azureml-train-core~=1.60.0
Requires-Dist: portalocker>=1.5.2
Dynamic: author
Dynamic: description
Dynamic: description-content-type
Dynamic: home-page
Dynamic: keywords
Dynamic: license
Dynamic: license-file
Dynamic: requires-dist
Dynamic: requires-python
Dynamic: summary
